[{"SenderAddress":"Rosemary79@gmail.com","ReceiverAddress":"Wendy_Kirlin89@hotmail.com","Subject":"New Message","Body":"Dear {{FullName}}, thank you for using our services.","SentTime":"2022-12-12T13:21:36.4875024+01:00","IsSent":false,"IsDeleted":false,"DeletedDate":null,"CreatedDate":"2023-10-08T14:21:47.5213132+01:00","ModifiedDate":null,"Id":"900fbdec-c1be-4bb6-aca5-40bc96c7b8ea"},{"SenderAddress":"Harriet.Haag89@yahoo.com","ReceiverAddress":"Angel58@yahoo.com","Subject":"Your password has been changes","Body":"Dear {{FullName}}, welcome to our system","SentTime":"2023-05-14T20:42:05.1962+01:00","IsSent":true,"IsDeleted":false,"DeletedDate":null,"CreatedDate":"2023-10-08T14:21:47.5213176+01:00","ModifiedDate":null,"Id":"e64706c8-6bb8-4b6e-bdb0-243bec2528ec"},{"SenderAddress":"Leland16@hotmail.com","ReceiverAddress":"Francis81@hotmail.com","Subject":"Thank You","Body":"Hello {{FullName}}, you've got a new message.","SentTime":"2023-07-08T19:15:09.917103+01:00","IsSent":true,"IsDeleted":false,"DeletedDate":null,"CreatedDate":"2023-10-08T14:21:47.521318+01:00","ModifiedDate":null,"Id":"4914c8d4-f65c-49b3-8fa0-48d4ea6c6159"},{"SenderAddress":"Lora.Cartwright62@yahoo.com","ReceiverAddress":"Ora.Schiller@gmail.com","Subject":"Truck Confirmation","Body":"Dear {{FullName}}, welcome to our system","SentTime":"2023-05-19T22:02:01.4208976+01:00","IsSent":false,"IsDeleted":false,"DeletedDate":null,"CreatedDate":"2023-10-08T14:21:47.5213183+01:00","ModifiedDate":null,"Id":"5cba6af7-c5ec-4069-a185-59e3eba4e0d8"},{"SenderAddress":"Delores_Gaylord@yahoo.com","ReceiverAddress":"Maurice35@gmail.com","Subject":"Welcome to our system","Body":"Dear {{FullName}}, thank you for using our services.","SentTime":"2022-11-20T04:14:44.0324321+01:00","IsSent":true,"IsDeleted":false,"DeletedDate":null,"CreatedDate":"2023-10-08T14:21:47.5213185+01:00","ModifiedDate":null,"Id":"cbd19d20-8f20-47ad-b2ad-3d88b27bca22"},{"SenderAddress":"Rickey.Wiza@hotmail.com","ReceiverAddress":"Tracy_Hirthe@hotmail.com","Subject":"Your password has been changes","Body":"Dear {{FullName}}, Your password has been changed.","SentTime":"2023-08-06T10:36:22.9150905+01:00","IsSent":true,"IsDeleted":false,"DeletedDate":null,"CreatedDate":"2023-10-08T14:21:47.5213188+01:00","ModifiedDate":null,"Id":"17ec1b56-7c57-4b89-9631-1740aa39ee91"},{"SenderAddress":"Vicky96@gmail.com","ReceiverAddress":"Randall.Torphy@yahoo.com","Subject":"Your password has been changes","Body":"Dear {{FullName}}, your truck has been confirmed.","SentTime":"2023-02-13T00:35:16.1780129+01:00","IsSent":true,"IsDeleted":false,"DeletedDate":null,"CreatedDate":"2023-10-08T14:21:47.521319+01:00","ModifiedDate":null,"Id":"640aa14c-06bc-45d5-9223-4e6d488750cb"},{"SenderAddress":"Bridget_Ebert@hotmail.com","ReceiverAddress":"Jack66@gmail.com","Subject":"Truck Confirmation","Body":"Dear {{FullName}}, Your password has been changed.","SentTime":"2023-01-08T16:14:25.8547359+01:00","IsSent":true,"IsDeleted":false,"DeletedDate":null,"CreatedDate":"2023-10-08T14:21:47.5213193+01:00","ModifiedDate":null,"Id":"ce80172c-cad8-4430-9280-661f9fd34f13"},{"SenderAddress":"Pedro46@gmail.com","ReceiverAddress":"Justin99@yahoo.com","Subject":"Truck Confirmation","Body":"Dear {{FullName}}, welcome to our system","SentTime":"2023-05-14T00:06:49.154028+01:00","IsSent":true,"IsDeleted":false,"DeletedDate":null,"CreatedDate":"2023-10-08T14:21:47.5213195+01:00","ModifiedDate":null,"Id":"dd236187-6375-4bbc-9ab1-e59eabea4546"},{"SenderAddress":"Angel95@gmail.com","ReceiverAddress":"Dwayne71@yahoo.com","Subject":"Thank You","Body":"Dear {{FullName}}, thank you for using our services.","SentTime":"2023-06-14T17:17:35.6999903+01:00","IsSent":false,"IsDeleted":false,"DeletedDate":null,"CreatedDate":"2023-10-08T14:21:47.5213198+01:00","ModifiedDate":null,"Id":"b2dbbdd9-e4be-4bee-9959-c05dbb591a0d"},{"SenderAddress":"Amos.Reichel@gmail.com","ReceiverAddress":"Leland16@hotmail.com","Subject":"New Message","Body":"Dear {{FullName}}, welcome to our system","SentTime":"2023-07-22T23:38:25.8515661+01:00","IsSent":true,"IsDeleted":false,"DeletedDate":null,"CreatedDate":"2023-10-08T14:21:47.52132+01:00","ModifiedDate":null,"Id":"6f92e9f7-e649-4987-9ceb-a358b9e94c59"},{"SenderAddress":"Lester53@hotmail.com","ReceiverAddress":"Jonathan60@hotmail.com","Subject":"New Message","Body":"Dear {{FullName}}, thank you for using our services.","SentTime":"2023-06-09T22:22:29.7623505+01:00","IsSent":true,"IsDeleted":false,"DeletedDate":null,"CreatedDate":"2023-10-08T14:21:47.5213203+01:00","ModifiedDate":null,"Id":"d8b61797-c4c2-46cd-a773-02f36f57dce8"},{"SenderAddress":"Sergio.Kuhn@gmail.com","ReceiverAddress":"Joanna.Miller60@gmail.com","Subject":"Thank You","Body":"Hello {{FullName}}, you've got a new message.","SentTime":"2023-05-23T09:22:33.2311483+01:00","IsSent":true,"IsDeleted":false,"DeletedDate":null,"CreatedDate":"2023-10-08T14:21:47.5213205+01:00","ModifiedDate":null,"Id":"1720147b-3a7e-48c5-8bc1-991b4c98bed7"},{"SenderAddress":"Gilberto.Bernier@hotmail.com","ReceiverAddress":"Garry_Shanahan67@hotmail.com","Subject":"New Message","Body":"Hello {{FullName}}, you've got a new message.","SentTime":"2023-01-09T13:43:07.4970094+01:00","IsSent":false,"IsDeleted":false,"DeletedDate":null,"CreatedDate":"2023-10-08T14:21:47.5213207+01:00","ModifiedDate":null,"Id":"03ef39bc-f55d-4ee9-9e90-07c9bbfac2d2"},{"SenderAddress":"Ora.Schiller@gmail.com","ReceiverAddress":"Gilbert.Gutmann@hotmail.com","Subject":"Truck Confirmation","Body":"Hello {{FullName}}, you've got a new message.","SentTime":"2022-12-25T02:12:58.4845603+01:00","IsSent":false,"IsDeleted":false,"DeletedDate":null,"CreatedDate":"2023-10-08T14:21:47.521321+01:00","ModifiedDate":null,"Id":"a144312e-deb8-427a-958a-1d2eb0b80900"},{"SenderAddress":"Virgil_Kessler@hotmail.com","ReceiverAddress":"Marcos.Rohan@hotmail.com","Subject":"Truck Confirmation","Body":"Dear {{FullName}}, thank you for using our services.","SentTime":"2023-06-22T05:03:56.922868+01:00","IsSent":false,"IsDeleted":false,"DeletedDate":null,"CreatedDate":"2023-10-08T14:21:47.5213212+01:00","ModifiedDate":null,"Id":"79ae87ad-2b66-4f4c-91a0-997ee25bc20a"},{"SenderAddress":"Mack49@hotmail.com","ReceiverAddress":"Gwen.Mertz25@yahoo.com","Subject":"Your password has been changes","Body":"Dear {{FullName}}, thank you for using our services.","SentTime":"2023-04-06T00:25:16.996484+01:00","IsSent":true,"IsDeleted":false,"DeletedDate":null,"CreatedDate":"2023-10-08T14:21:47.5213215+01:00","ModifiedDate":null,"Id":"77a80160-47ad-4186-844f-71d9352445f0"},{"SenderAddress":"Vicky96@gmail.com","ReceiverAddress":"Francis81@hotmail.com","Subject":"Welcome to our system","Body":"Dear {{FullName}}, Your password has been changed.","SentTime":"2023-06-09T11:25:12.5904076+01:00","IsSent":true,"IsDeleted":false,"DeletedDate":null,"CreatedDate":"2023-10-08T14:21:47.5213217+01:00","ModifiedDate":null,"Id":"4df1d937-ee42-4657-8e63-38af502f5531"},{"SenderAddress":"Cynthia_DuBuque@yahoo.com","ReceiverAddress":"Faye.Ratke@yahoo.com","Subject":"Your password has been changes","Body":"Dear {{FullName}}, welcome to our system","SentTime":"2023-03-24T10:16:39.2215889+01:00","IsSent":true,"IsDeleted":false,"DeletedDate":null,"CreatedDate":"2023-10-08T14:21:47.521322+01:00","ModifiedDate":null,"Id":"5b39f1fc-9239-4720-8a95-b20062e3b046"},{"SenderAddress":"Joanna.Miller60@gmail.com","ReceiverAddress":"Marianne30@gmail.com","Subject":"Thank You","Body":"Hello {{FullName}}, you've got a new message.","SentTime":"2023-07-22T00:36:47.8858084+01:00","IsSent":false,"IsDeleted":false,"DeletedDate":null,"CreatedDate":"2023-10-08T14:21:47.5213222+01:00","ModifiedDate":null,"Id":"6598f77c-c6f7-413a-b5b7-2d3e2c12cc11"}]