[{"SenderAddress":"Hope79@gmail.com","ReceiverAddress":"Kellie83@yahoo.com","Subject":"Your password has been changes","Body":"Dear {{FullName}}, thank you for using our services.","SentTime":"2023-07-10T20:17:14.0103302+05:00","IsSent":true,"IsDeleted":false,"DeletedDate":null,"CreatedDate":"2023-10-03T10:30:06.4009462+05:00","ModifiedDate":null,"Id":"0b707c91-734f-4e57-b151-0b70af61e8df"},{"SenderAddress":"Jamie_Wuckert14@hotmail.com","ReceiverAddress":"James.Abshire@yahoo.com","Subject":"Thank You","Body":"Dear {{FullName}}, welcome to our system","SentTime":"2023-08-26T19:27:51.5115177+05:00","IsSent":true,"IsDeleted":false,"DeletedDate":null,"CreatedDate":"2023-10-03T10:30:06.4009815+05:00","ModifiedDate":null,"Id":"4da251e8-984b-4d85-b3cf-3e56a4b75910"},{"SenderAddress":"Kristina_Nicolas7@hotmail.com","ReceiverAddress":"Cynthia.Mante@hotmail.com","Subject":"Truck Confirmation","Body":"Dear {{FullName}}, thank you for using our services.","SentTime":"2023-01-10T16:55:33.0952334+05:00","IsSent":false,"IsDeleted":false,"DeletedDate":null,"CreatedDate":"2023-10-03T10:30:06.4009823+05:00","ModifiedDate":null,"Id":"402b29b3-fc32-4d88-a7fe-5bcb87b3bc30"},{"SenderAddress":"Kenny.Blanda1@gmail.com","ReceiverAddress":"Jean_Marks@hotmail.com","Subject":"New Message","Body":"Dear {{FullName}}, welcome to our system","SentTime":"2023-09-29T20:03:36.8227715+05:00","IsSent":true,"IsDeleted":false,"DeletedDate":null,"CreatedDate":"2023-10-03T10:30:06.4009826+05:00","ModifiedDate":null,"Id":"49c21ada-1fb0-4a56-94de-222962451f66"},{"SenderAddress":"Jeannie_Huel87@yahoo.com","ReceiverAddress":"admin@gmail.com","Subject":"New Message","Body":"Hello {{FullName}}, you've got a new message.","SentTime":"2023-05-25T20:40:00.0042036+05:00","IsSent":true,"IsDeleted":false,"DeletedDate":null,"CreatedDate":"2023-10-03T10:30:06.4009829+05:00","ModifiedDate":null,"Id":"03d4ea29-19f7-4146-b0da-045e9951ec9d"},{"SenderAddress":"Garry_Herzog@gmail.com","ReceiverAddress":"Wilbur31@hotmail.com","Subject":"Your password has been changes","Body":"Dear {{FullName}}, Your password has been changed.","SentTime":"2022-12-28T04:41:29.5619779+05:00","IsSent":false,"IsDeleted":false,"DeletedDate":null,"CreatedDate":"2023-10-03T10:30:06.4009833+05:00","ModifiedDate":null,"Id":"059c3af8-de98-4914-b5fc-2747d059fded"},{"SenderAddress":"Margarita19@yahoo.com","ReceiverAddress":"Randal_Labadie@yahoo.com","Subject":"Your password has been changes","Body":"Dear {{FullName}}, Your password has been changed.","SentTime":"2022-10-22T03:49:04.5013195+05:00","IsSent":true,"IsDeleted":false,"DeletedDate":null,"CreatedDate":"2023-10-03T10:30:06.4009836+05:00","ModifiedDate":null,"Id":"50d87022-6712-4bd2-8d20-deea8b734b78"},{"SenderAddress":"Hilda9@hotmail.com","ReceiverAddress":"Kristina.Schmitt13@gmail.com","Subject":"Your password has been changes","Body":"Dear {{FullName}}, welcome to our system","SentTime":"2023-05-31T20:35:56.8565437+05:00","IsSent":true,"IsDeleted":false,"DeletedDate":null,"CreatedDate":"2023-10-03T10:30:06.4009838+05:00","ModifiedDate":null,"Id":"e95ce13b-e28f-48c9-bf18-23a13e289609"},{"SenderAddress":"Darrel.Sauer35@gmail.com","ReceiverAddress":"Marianne_Cole87@yahoo.com","Subject":"Welcome to our system","Body":"Dear {{FullName}}, Your password has been changed.","SentTime":"2023-08-20T06:42:23.8264767+05:00","IsSent":true,"IsDeleted":false,"DeletedDate":null,"CreatedDate":"2023-10-03T10:30:06.4009841+05:00","ModifiedDate":null,"Id":"f7d45591-408d-4be9-9ca9-df8ecd9ed042"},{"SenderAddress":"Clifford_Grimes70@hotmail.com","ReceiverAddress":"Angelina.Leannon@hotmail.com","Subject":"Thank You","Body":"Hello {{FullName}}, you've got a new message.","SentTime":"2023-06-17T04:39:49.2282134+05:00","IsSent":true,"IsDeleted":false,"DeletedDate":null,"CreatedDate":"2023-10-03T10:30:06.4009844+05:00","ModifiedDate":null,"Id":"0bdd050a-196d-41bd-baa0-6666336ef883"},{"SenderAddress":"Jean_Marks@hotmail.com","ReceiverAddress":"Bill.Kris15@hotmail.com","Subject":"Your password has been changes","Body":"Hello {{FullName}}, you've got a new message.","SentTime":"2022-11-19T11:42:43.900466+05:00","IsSent":true,"IsDeleted":false,"DeletedDate":null,"CreatedDate":"2023-10-03T10:30:06.4009846+05:00","ModifiedDate":null,"Id":"78ece56e-8031-4702-9bb2-f6f5d34e88d0"},{"SenderAddress":"Randal_Labadie@yahoo.com","ReceiverAddress":"Leslie.Erdman@yahoo.com","Subject":"New Message","Body":"Hello {{FullName}}, you've got a new message.","SentTime":"2023-08-14T02:49:17.1663761+05:00","IsSent":false,"IsDeleted":false,"DeletedDate":null,"CreatedDate":"2023-10-03T10:30:06.4009849+05:00","ModifiedDate":null,"Id":"5efebb52-b2f6-488a-89dc-ab62f66a0718"},{"SenderAddress":"Nina_Sipes4@hotmail.com","ReceiverAddress":"James.Abshire@yahoo.com","Subject":"Your password has been changes","Body":"Dear {{FullName}}, thank you for using our services.","SentTime":"2023-08-07T00:00:08.815327+05:00","IsSent":true,"IsDeleted":false,"DeletedDate":null,"CreatedDate":"2023-10-03T10:30:06.4009852+05:00","ModifiedDate":null,"Id":"bb2c1c51-3223-4c36-854f-16dc1aadfde8"},{"SenderAddress":"Viola.Wolf76@gmail.com","ReceiverAddress":"Eva_Wehner@gmail.com","Subject":"Welcome to our system","Body":"Dear {{FullName}}, Your password has been changed.","SentTime":"2023-08-30T19:54:01.021973+05:00","IsSent":false,"IsDeleted":false,"DeletedDate":null,"CreatedDate":"2023-10-03T10:30:06.4009856+05:00","ModifiedDate":null,"Id":"9b431d51-a996-4a9d-845b-660ae70c1e59"},{"SenderAddress":"Jerome26@hotmail.com","ReceiverAddress":"Penny_Dietrich@yahoo.com","Subject":"Welcome to our system","Body":"Hello {{FullName}}, you've got a new message.","SentTime":"2023-08-04T12:44:08.8384743+05:00","IsSent":true,"IsDeleted":false,"DeletedDate":null,"CreatedDate":"2023-10-03T10:30:06.4009859+05:00","ModifiedDate":null,"Id":"881a72b4-aa62-4c07-859a-e3d62ab091e2"},{"SenderAddress":"Vicky_Schaden96@gmail.com","ReceiverAddress":"Greg.Lowe96@yahoo.com","Subject":"Truck Confirmation","Body":"Dear {{FullName}}, welcome to our system","SentTime":"2022-10-27T23:38:29.0830642+05:00","IsSent":true,"IsDeleted":false,"DeletedDate":null,"CreatedDate":"2023-10-03T10:30:06.4009861+05:00","ModifiedDate":null,"Id":"121da1e1-8c17-42df-8bef-7301612f4ca6"},{"SenderAddress":"Cynthia.Mante@hotmail.com","ReceiverAddress":"Phillip_Kulas@gmail.com","Subject":"Thank You","Body":"Dear {{FullName}}, thank you for using our services.","SentTime":"2023-08-31T08:54:18.3362876+05:00","IsSent":false,"IsDeleted":false,"DeletedDate":null,"CreatedDate":"2023-10-03T10:30:06.4009864+05:00","ModifiedDate":null,"Id":"4bec47bc-8862-44d5-9ee7-0fa61d2ef60e"},{"SenderAddress":"Kristina.Schmitt13@gmail.com","ReceiverAddress":"Margarita.Heaney63@yahoo.com","Subject":"Truck Confirmation","Body":"Hello {{FullName}}, you've got a new message.","SentTime":"2023-08-18T14:47:38.8484097+05:00","IsSent":true,"IsDeleted":false,"DeletedDate":null,"CreatedDate":"2023-10-03T10:30:06.4009866+05:00","ModifiedDate":null,"Id":"a9e26caa-022b-4a66-8d35-8fbbe7d5a740"},{"SenderAddress":"Jerome26@hotmail.com","ReceiverAddress":"Marianne_Cole87@yahoo.com","Subject":"Truck Confirmation","Body":"Dear {{FullName}}, thank you for using our services.","SentTime":"2023-08-22T17:42:45.9337978+05:00","IsSent":true,"IsDeleted":false,"DeletedDate":null,"CreatedDate":"2023-10-03T10:30:06.4009869+05:00","ModifiedDate":null,"Id":"d1cc4c09-ea36-4265-b4ca-60de1fcead19"},{"SenderAddress":"Marianne_Cole87@yahoo.com","ReceiverAddress":"Jean_Marks@hotmail.com","Subject":"Thank You","Body":"Dear {{FullName}}, Your password has been changed.","SentTime":"2023-04-29T13:05:35.8021782+05:00","IsSent":true,"IsDeleted":false,"DeletedDate":null,"CreatedDate":"2023-10-03T10:30:06.4009872+05:00","ModifiedDate":null,"Id":"eea66159-02e4-40a0-a4db-34aee5a29dcf"},{"SenderAddress":"Eddie_Rath68@gmail.com","ReceiverAddress":"Vicky_Schaden96@gmail.com","Subject":"Thank You","Body":"Dear {{FullName}}, thank you for using our services.","SentTime":"2023-07-26T22:28:44.4441607+05:00","IsSent":false,"IsDeleted":false,"DeletedDate":null,"CreatedDate":"2023-10-03T10:30:06.4009875+05:00","ModifiedDate":null,"Id":"8a75e447-e6d7-46dc-9a2e-0aa09b042c10"},{"SenderAddress":"Kerry30@hotmail.com","ReceiverAddress":"Cynthia.Mante@hotmail.com","Subject":"Your password has been changes","Body":"Dear {{FullName}}, Your password has been changed.","SentTime":"2023-03-21T00:15:26.0831011+05:00","IsSent":true,"IsDeleted":false,"DeletedDate":null,"CreatedDate":"2023-10-03T10:30:06.4009882+05:00","ModifiedDate":null,"Id":"fc5dc1ba-87a8-4a83-b074-4af7d3dd02bd"},{"SenderAddress":"Marta_Hirthe@hotmail.com","ReceiverAddress":"Woodrow14@gmail.com","Subject":"Welcome to our system","Body":"Dear {{FullName}}, your truck has been confirmed.","SentTime":"2023-07-25T21:08:42.8726499+05:00","IsSent":true,"IsDeleted":false,"DeletedDate":null,"CreatedDate":"2023-10-03T10:30:06.4009884+05:00","ModifiedDate":null,"Id":"16fa9f00-6767-4be9-bbd6-24f0e6a1cc43"},{"SenderAddress":"Jerald53@hotmail.com","ReceiverAddress":"Keith_Hand@hotmail.com","Subject":"Welcome to our system","Body":"Dear {{FullName}}, Your password has been changed.","SentTime":"2023-08-01T21:01:18.1209807+05:00","IsSent":false,"IsDeleted":false,"DeletedDate":null,"CreatedDate":"2023-10-03T10:30:06.4009886+05:00","ModifiedDate":null,"Id":"19a72b0a-e520-42da-b1a2-be12f5ae49d0"},{"SenderAddress":"Lynda_Gusikowski76@yahoo.com","ReceiverAddress":"Felipe77@yahoo.com","Subject":"Your password has been changes","Body":"Dear {{FullName}}, thank you for using our services.","SentTime":"2023-05-11T13:52:03.6515054+05:00","IsSent":false,"IsDeleted":false,"DeletedDate":null,"CreatedDate":"2023-10-03T10:30:06.4009889+05:00","ModifiedDate":null,"Id":"b6335a75-8121-4eb8-9fc7-904fb9ddb43c"},{"SenderAddress":"Lynda_Gusikowski76@yahoo.com","ReceiverAddress":"Dallas86@yahoo.com","Subject":"New Message","Body":"Dear {{FullName}}, your truck has been confirmed.","SentTime":"2023-06-23T16:01:01.5197073+05:00","IsSent":true,"IsDeleted":false,"DeletedDate":null,"CreatedDate":"2023-10-03T10:30:06.4009891+05:00","ModifiedDate":null,"Id":"4e23b38a-3779-40c8-9f80-10673686cfb7"},{"SenderAddress":"Eva_Wehner@gmail.com","ReceiverAddress":"Phillip_Kulas@gmail.com","Subject":"Thank You","Body":"Hello {{FullName}}, you've got a new message.","SentTime":"2022-12-13T09:51:12.968283+05:00","IsSent":false,"IsDeleted":false,"DeletedDate":null,"CreatedDate":"2023-10-03T10:30:06.4009893+05:00","ModifiedDate":null,"Id":"fba062cf-aae9-4100-ae96-9e88e48423aa"},{"SenderAddress":"Darrel.Kulas13@gmail.com","ReceiverAddress":"Seth.Kiehn54@hotmail.com","Subject":"New Message","Body":"Dear {{FullName}}, thank you for using our services.","SentTime":"2023-02-25T20:27:20.794783+05:00","IsSent":false,"IsDeleted":false,"DeletedDate":null,"CreatedDate":"2023-10-03T10:30:06.4009896+05:00","ModifiedDate":null,"Id":"511ed875-66ed-4712-ac96-50b51a090850"},{"SenderAddress":"Clifford_Grimes70@hotmail.com","ReceiverAddress":"Seth.Kiehn54@hotmail.com","Subject":"Truck Confirmation","Body":"Dear {{FullName}}, thank you for using our services.","SentTime":"2022-10-28T07:37:00.2432637+05:00","IsSent":false,"IsDeleted":false,"DeletedDate":null,"CreatedDate":"2023-10-03T10:30:06.4009898+05:00","ModifiedDate":null,"Id":"cdacb6cf-037b-432a-8eed-31221774f3e8"},{"SenderAddress":"Dewey.Medhurst@gmail.com","ReceiverAddress":"Whitney6@yahoo.com","Subject":"Thank You","Body":"Hello {{FullName}}, you've got a new message.","SentTime":"2023-03-23T05:57:13.1036535+05:00","IsSent":false,"IsDeleted":false,"DeletedDate":null,"CreatedDate":"2023-10-03T10:30:06.4009901+05:00","ModifiedDate":null,"Id":"77014c2e-2dd1-4086-ad78-53d21fda4235"},{"SenderAddress":"Clinton_Schaden@yahoo.com","ReceiverAddress":"Clinton_Schaden@yahoo.com","Subject":"Truck Confirmation","Body":"Dear {{FullName}}, thank you for using our services.","SentTime":"2023-08-18T13:28:20.9895979+05:00","IsSent":false,"IsDeleted":false,"DeletedDate":null,"CreatedDate":"2023-10-03T10:30:06.4009904+05:00","ModifiedDate":null,"Id":"3136ce63-781b-4722-be96-832462f4592d"},{"SenderAddress":"admin@gmail.com","ReceiverAddress":"James18@gmail.com","Subject":"Truck Confirmation","Body":"Dear {{FullName}}, Your password has been changed.","SentTime":"2023-05-21T05:45:12.130079+05:00","IsSent":false,"IsDeleted":false,"DeletedDate":null,"CreatedDate":"2023-10-03T10:30:06.4009906+05:00","ModifiedDate":null,"Id":"a2414ea3-7370-4530-ae0f-3fe4c4d62b89"},{"SenderAddress":"Naomi_Hayes51@yahoo.com","ReceiverAddress":"Wesley.Fay@hotmail.com","Subject":"Your password has been changes","Body":"Dear {{FullName}}, welcome to our system","SentTime":"2023-08-03T15:54:16.128189+05:00","IsSent":false,"IsDeleted":false,"DeletedDate":null,"CreatedDate":"2023-10-03T10:30:06.4009909+05:00","ModifiedDate":null,"Id":"9b296e43-39e6-484b-948e-e2e1c43ae3a1"},{"SenderAddress":"Tiffany.Brakus@gmail.com","ReceiverAddress":"Latoya_VonRueden@yahoo.com","Subject":"Welcome to our system","Body":"Dear {{FullName}}, Your password has been changed.","SentTime":"2023-02-28T11:25:30.1240251+05:00","IsSent":true,"IsDeleted":false,"DeletedDate":null,"CreatedDate":"2023-10-03T10:30:06.4009912+05:00","ModifiedDate":null,"Id":"9f7a9781-5800-4d8b-908b-845b8da215d1"},{"SenderAddress":"Kristina.Schmitt13@gmail.com","ReceiverAddress":"Jeannie_Huel87@yahoo.com","Subject":"New Message","Body":"Hello {{FullName}}, you've got a new message.","SentTime":"2023-07-13T22:54:28.2156295+05:00","IsSent":false,"IsDeleted":false,"DeletedDate":null,"CreatedDate":"2023-10-03T10:30:06.4009915+05:00","ModifiedDate":null,"Id":"c1aa5d74-1551-41fe-a27b-c3d638705d27"},{"SenderAddress":"Kerry30@hotmail.com","ReceiverAddress":"Greg.Lowe96@yahoo.com","Subject":"Welcome to our system","Body":"Dear {{FullName}}, welcome to our system","SentTime":"2022-12-23T00:39:51.729828+05:00","IsSent":false,"IsDeleted":false,"DeletedDate":null,"CreatedDate":"2023-10-03T10:30:06.4009917+05:00","ModifiedDate":null,"Id":"358cbf22-c44c-41c6-babe-d983ce5293df"},{"SenderAddress":"Ismael.Goldner97@yahoo.com","ReceiverAddress":"Kimberly94@yahoo.com","Subject":"Your password has been changes","Body":"Dear {{FullName}}, your truck has been confirmed.","SentTime":"2023-01-24T16:14:10.6111353+05:00","IsSent":false,"IsDeleted":false,"DeletedDate":null,"CreatedDate":"2023-10-03T10:30:06.400992+05:00","ModifiedDate":null,"Id":"8233f6c9-89d6-41c9-992a-82a0223dd740"},{"SenderAddress":"Milton2@yahoo.com","ReceiverAddress":"Clinton_Schaden@yahoo.com","Subject":"Your password has been changes","Body":"Dear {{FullName}}, your truck has been confirmed.","SentTime":"2023-05-05T02:40:49.5594598+05:00","IsSent":false,"IsDeleted":false,"DeletedDate":null,"CreatedDate":"2023-10-03T10:30:06.4009923+05:00","ModifiedDate":null,"Id":"71c28a9a-1ebf-4912-a650-31c32f7ac8e7"},{"SenderAddress":"Christine.Orn1@yahoo.com","ReceiverAddress":"Ben_Breitenberg@gmail.com","Subject":"Welcome to our system","Body":"Dear {{FullName}}, your truck has been confirmed.","SentTime":"2022-10-04T14:35:58.1522137+05:00","IsSent":true,"IsDeleted":false,"DeletedDate":null,"CreatedDate":"2023-10-03T10:30:06.4009925+05:00","ModifiedDate":null,"Id":"bf1694eb-6150-4262-b8bb-1d4298a78019"},{"SenderAddress":"Colin.Runolfsdottir@gmail.com","ReceiverAddress":"Whitney6@yahoo.com","Subject":"Welcome to our system","Body":"Dear {{FullName}}, your truck has been confirmed.","SentTime":"2023-06-02T04:09:34.4380747+05:00","IsSent":true,"IsDeleted":false,"DeletedDate":null,"CreatedDate":"2023-10-03T10:30:06.4009928+05:00","ModifiedDate":null,"Id":"ca665bc0-9de5-4dd6-bfab-bd9e88db549a"},{"SenderAddress":"Clinton_Schaden@yahoo.com","ReceiverAddress":"Cynthia.Mante@hotmail.com","Subject":"Your password has been changes","Body":"Dear {{FullName}}, thank you for using our services.","SentTime":"2023-08-30T23:07:24.1591883+05:00","IsSent":false,"IsDeleted":false,"DeletedDate":null,"CreatedDate":"2023-10-03T10:30:06.4009931+05:00","ModifiedDate":null,"Id":"833ce3a1-8122-49b8-b27a-c170701754dc"},{"SenderAddress":"Margarita19@yahoo.com","ReceiverAddress":"Cameron.Ferry96@yahoo.com","Subject":"Your password has been changes","Body":"Dear {{FullName}}, your truck has been confirmed.","SentTime":"2023-01-21T14:55:16.1285941+05:00","IsSent":false,"IsDeleted":false,"DeletedDate":null,"CreatedDate":"2023-10-03T10:30:06.4009933+05:00","ModifiedDate":null,"Id":"68940812-d52e-4aca-a511-1f50e8d2e574"},{"SenderAddress":"Jerald53@hotmail.com","ReceiverAddress":"Woodrow14@gmail.com","Subject":"Welcome to our system","Body":"Dear {{FullName}}, Your password has been changed.","SentTime":"2023-01-16T10:52:16.5750642+05:00","IsSent":false,"IsDeleted":false,"DeletedDate":null,"CreatedDate":"2023-10-03T10:30:06.4009936+05:00","ModifiedDate":null,"Id":"4652d63f-4091-4c83-9d46-70f37439ceb6"},{"SenderAddress":"Greg.Lowe96@yahoo.com","ReceiverAddress":"Randall_Howe@yahoo.com","Subject":"Thank You","Body":"Dear {{FullName}}, your truck has been confirmed.","SentTime":"2023-06-27T20:08:45.2889741+05:00","IsSent":true,"IsDeleted":false,"DeletedDate":null,"CreatedDate":"2023-10-03T10:30:06.4009938+05:00","ModifiedDate":null,"Id":"ec937da6-4f2d-4cad-a7d5-1c0485cd2a22"},{"SenderAddress":"Jean_Parker36@hotmail.com","ReceiverAddress":"Ella.Von@gmail.com","Subject":"Welcome to our system","Body":"Dear {{FullName}}, your truck has been confirmed.","SentTime":"2023-07-16T04:38:42.5659882+05:00","IsSent":false,"IsDeleted":false,"DeletedDate":null,"CreatedDate":"2023-10-03T10:30:06.4009941+05:00","ModifiedDate":null,"Id":"0038f2e1-558e-4103-9ba9-aa0869c1d6e4"},{"SenderAddress":"Wesley.Fay@hotmail.com","ReceiverAddress":"Garry0@hotmail.com","Subject":"Truck Confirmation","Body":"Dear {{FullName}}, thank you for using our services.","SentTime":"2023-08-22T07:28:53.2682325+05:00","IsSent":false,"IsDeleted":false,"DeletedDate":null,"CreatedDate":"2023-10-03T10:30:06.4009943+05:00","ModifiedDate":null,"Id":"4790aa87-5715-436d-aaf3-089e09bd17f5"},{"SenderAddress":"Kristina_Nicolas7@hotmail.com","ReceiverAddress":"Darrel.Kulas13@gmail.com","Subject":"Thank You","Body":"Dear {{FullName}}, welcome to our system","SentTime":"2022-11-17T06:44:12.2737484+05:00","IsSent":true,"IsDeleted":false,"DeletedDate":null,"CreatedDate":"2023-10-03T10:30:06.4009946+05:00","ModifiedDate":null,"Id":"cfff761b-ac97-4148-ba73-ec80fef61066"},{"SenderAddress":"Cynthia.Mante@hotmail.com","ReceiverAddress":"Lyle86@gmail.com","Subject":"Thank You","Body":"Hello {{FullName}}, you've got a new message.","SentTime":"2023-09-05T09:54:07.0478969+05:00","IsSent":true,"IsDeleted":false,"DeletedDate":null,"CreatedDate":"2023-10-03T10:30:06.4009949+05:00","ModifiedDate":null,"Id":"1a7c1367-59b7-480c-80be-37b3e26fac38"},{"SenderAddress":"Emmett27@yahoo.com","ReceiverAddress":"Bill.Kris15@hotmail.com","Subject":"Thank You","Body":"Dear {{FullName}}, your truck has been confirmed.","SentTime":"2022-11-09T10:11:08.6392436+05:00","IsSent":true,"IsDeleted":false,"DeletedDate":null,"CreatedDate":"2023-10-03T10:30:06.4009952+05:00","ModifiedDate":null,"Id":"37c45ad7-fe22-4651-8130-146de49ef48b"},{"SenderAddress":"Ismael.Goldner97@yahoo.com","ReceiverAddress":"Paulette_Fadel60@gmail.com","Subject":"Welcome to our system","Body":"Dear {{FullName}}, your truck has been confirmed.","SentTime":"2023-09-09T21:35:54.8864636+05:00","IsSent":true,"IsDeleted":false,"DeletedDate":null,"CreatedDate":"2023-10-03T10:30:06.4009954+05:00","ModifiedDate":null,"Id":"fb0c4dab-1704-41f1-ac33-c3cc33c2af7b"},{"SenderAddress":"sultonbek.rakhimov@gmail.com","ReceiverAddress":"Ruby_Stroman@hotmail.com","Subject":"Welcome to our system","Body":"Dear  RubyStroman, welcome to our system","SentTime":"2023-10-04T20:02:02.2974355+05:00","IsSent":false,"IsDeleted":false,"DeletedDate":null,"CreatedDate":"2023-10-04T20:02:02.3062582+05:00","ModifiedDate":null,"Id":"01643ec1-6f26-4b55-9162-008008992c89"},{"SenderAddress":"sultonbek.rakhimov@gmail.com","ReceiverAddress":"Ruby_Stroman@hotmail.com","Subject":"Welcome to our system","Body":"Dear  RubyStroman, welcome to our system","SentTime":"2023-10-04T20:02:02.2974084+05:00","IsSent":false,"IsDeleted":false,"DeletedDate":null,"CreatedDate":"2023-10-04T20:02:02.306382+05:00","ModifiedDate":null,"Id":"a424feff-5be6-485c-ba24-ced4c8ae7d16"}]