[{"FirstName":"Calvin","LastName":"Barrows","EmailAddress":"Calvin_Barrows71@hotmail.com","IsDeleted":false,"DeletedDate":null,"CreatedDate":"2023-10-03T01:06:51.5288912-04:00","ModifiedDate":null,"Id":"13b6258f-fc57-423a-bf1f-ecef31630f59"},{"FirstName":"Tracey","LastName":"Price","EmailAddress":"Tracey.Price@gmail.com","IsDeleted":false,"DeletedDate":null,"CreatedDate":"2023-10-03T01:06:51.529049-04:00","ModifiedDate":null,"Id":"f18c3f59-f185-4d2d-a57c-258cb55e9e99"},{"FirstName":"June","LastName":"Legros","EmailAddress":"June_Legros@yahoo.com","IsDeleted":false,"DeletedDate":null,"CreatedDate":"2023-10-03T01:06:51.52907-04:00","ModifiedDate":null,"Id":"84395261-1cec-40ef-b4bf-4a483b6274e2"},{"FirstName":"Francis","LastName":"Hartmann","EmailAddress":"Francis.Hartmann77@hotmail.com","IsDeleted":false,"DeletedDate":null,"CreatedDate":"2023-10-03T01:06:51.5290703-04:00","ModifiedDate":null,"Id":"fbb45abd-1e81-41b9-866d-e1a491a26bc3"},{"FirstName":"Johnnie","LastName":"Bode","EmailAddress":"Johnnie48@gmail.com","IsDeleted":false,"DeletedDate":null,"CreatedDate":"2023-10-03T01:06:51.5290705-04:00","ModifiedDate":null,"Id":"a0e35c98-8c52-44e0-aca9-0f6ba9e8e145"},{"FirstName":"Saul","LastName":"Nicolas","EmailAddress":"Saul_Nicolas@gmail.com","IsDeleted":false,"DeletedDate":null,"CreatedDate":"2023-10-03T01:06:51.5290708-04:00","ModifiedDate":null,"Id":"f5b9bcc4-54bd-45a3-9bd0-3857057eead5"},{"FirstName":"Eileen","LastName":"Ullrich","EmailAddress":"Eileen_Ullrich92@yahoo.com","IsDeleted":false,"DeletedDate":null,"CreatedDate":"2023-10-03T01:06:51.5290711-04:00","ModifiedDate":null,"Id":"27ee84ab-f7d5-49a5-ae4e-41dc4291c4bb"},{"FirstName":"Allan","LastName":"Johns","EmailAddress":"Allan_Johns@gmail.com","IsDeleted":false,"DeletedDate":null,"CreatedDate":"2023-10-03T01:06:51.5290713-04:00","ModifiedDate":null,"Id":"c78f7e3e-df4e-4e49-a6b0-bc4c8d74df62"},{"FirstName":"Ginger","LastName":"Douglas","EmailAddress":"Ginger.Douglas97@hotmail.com","IsDeleted":false,"DeletedDate":null,"CreatedDate":"2023-10-03T01:06:51.5290715-04:00","ModifiedDate":null,"Id":"0d9c44e6-45e9-49f1-ba55-fc3548a6e81f"},{"FirstName":"Joey","LastName":"Gottlieb","EmailAddress":"Joey70@yahoo.com","IsDeleted":false,"DeletedDate":null,"CreatedDate":"2023-10-03T01:06:51.5290717-04:00","ModifiedDate":null,"Id":"bfaccd5a-ae17-4cc8-ad0a-236f455556b6"},{"FirstName":"Garrett","LastName":"Skiles","EmailAddress":"Garrett.Skiles76@yahoo.com","IsDeleted":false,"DeletedDate":null,"CreatedDate":"2023-10-03T01:06:51.529072-04:00","ModifiedDate":null,"Id":"99bf59b2-49de-425f-9a0a-b01e736efe55"},{"FirstName":"Megan","LastName":"Gleason","EmailAddress":"Megan_Gleason64@gmail.com","IsDeleted":false,"DeletedDate":null,"CreatedDate":"2023-10-03T01:06:51.5290721-04:00","ModifiedDate":null,"Id":"76bbfd49-0ec7-44e3-a373-11bc7aa7677d"},{"FirstName":"Clinton","LastName":"Olson","EmailAddress":"Clinton.Olson29@yahoo.com","IsDeleted":false,"DeletedDate":null,"CreatedDate":"2023-10-03T01:06:51.5290723-04:00","ModifiedDate":null,"Id":"f5a64621-12fa-410e-85ea-922ab986b509"},{"FirstName":"Donald","LastName":"Deckow","EmailAddress":"Donald.Deckow33@yahoo.com","IsDeleted":false,"DeletedDate":null,"CreatedDate":"2023-10-03T01:06:51.5290725-04:00","ModifiedDate":null,"Id":"91278509-b4b5-468f-9652-1029fe7de69c"},{"FirstName":"Lorenzo","LastName":"Bogan","EmailAddress":"Lorenzo35@yahoo.com","IsDeleted":false,"DeletedDate":null,"CreatedDate":"2023-10-03T01:06:51.5290726-04:00","ModifiedDate":null,"Id":"202f04e1-91a9-4c37-bb18-abbf9c1d8795"},{"FirstName":"Bradley","LastName":"Powlowski","EmailAddress":"Bradley10@yahoo.com","IsDeleted":false,"DeletedDate":null,"CreatedDate":"2023-10-03T01:06:51.5290728-04:00","ModifiedDate":null,"Id":"b748a17a-87ee-4b5e-8d42-18330299e6f5"},{"FirstName":"Keith","LastName":"O'Connell","EmailAddress":"Keith0@hotmail.com","IsDeleted":false,"DeletedDate":null,"CreatedDate":"2023-10-03T01:06:51.529073-04:00","ModifiedDate":null,"Id":"a83a124c-2dbd-4a6b-8768-ff25b18548e0"},{"FirstName":"Tara","LastName":"Metz","EmailAddress":"Tara16@gmail.com","IsDeleted":false,"DeletedDate":null,"CreatedDate":"2023-10-03T01:06:51.5290732-04:00","ModifiedDate":null,"Id":"229fddad-0b04-4dac-85e9-9ad7925627bd"},{"FirstName":"Frances","LastName":"Hammes","EmailAddress":"Frances25@yahoo.com","IsDeleted":false,"DeletedDate":null,"CreatedDate":"2023-10-03T01:06:51.5290734-04:00","ModifiedDate":null,"Id":"7ec9d280-4489-4ccc-8d8b-29cd16ded99f"},{"FirstName":"Al","LastName":"Howell","EmailAddress":"Al49@yahoo.com","IsDeleted":false,"DeletedDate":null,"CreatedDate":"2023-10-03T01:06:51.5290736-04:00","ModifiedDate":null,"Id":"c17d2593-37b1-49a2-a404-7775154eb5a3"},{"FirstName":"Benny","LastName":"Cassin","EmailAddress":"Benny.Cassin@yahoo.com","IsDeleted":false,"DeletedDate":null,"CreatedDate":"2023-10-03T01:06:51.529074-04:00","ModifiedDate":null,"Id":"fc812ae4-0eee-4601-8c46-dcb4f3f94717"},{"FirstName":"Paula","LastName":"Adams","EmailAddress":"Paula_Adams69@gmail.com","IsDeleted":false,"DeletedDate":null,"CreatedDate":"2023-10-03T01:06:51.5290741-04:00","ModifiedDate":null,"Id":"d437c40c-1c9a-47fd-9a60-cf410ff8a12d"},{"FirstName":"Lindsey","LastName":"Beahan","EmailAddress":"Lindsey_Beahan62@hotmail.com","IsDeleted":false,"DeletedDate":null,"CreatedDate":"2023-10-03T01:06:51.5290743-04:00","ModifiedDate":null,"Id":"590165ce-1bf2-4869-8788-4f1f36f2b70f"},{"FirstName":"Chelsea","LastName":"Schaden","EmailAddress":"Chelsea_Schaden57@hotmail.com","IsDeleted":false,"DeletedDate":null,"CreatedDate":"2023-10-03T01:06:51.5290745-04:00","ModifiedDate":null,"Id":"30837001-f801-4742-886e-c713132b30cd"},{"FirstName":"Wesley","LastName":"Kub","EmailAddress":"Wesley.Kub55@hotmail.com","IsDeleted":false,"DeletedDate":null,"CreatedDate":"2023-10-03T01:06:51.5290746-04:00","ModifiedDate":null,"Id":"96d99c5a-7b6e-4d83-97b5-bff13cecf484"},{"FirstName":"Sidney","LastName":"Heidenreich","EmailAddress":"Sidney33@gmail.com","IsDeleted":false,"DeletedDate":null,"CreatedDate":"2023-10-03T01:06:51.5290748-04:00","ModifiedDate":null,"Id":"1429f7ea-0ae4-4290-b0bf-e75e3f46bcbf"},{"FirstName":"Myron","LastName":"Wolf","EmailAddress":"Myron_Wolf3@yahoo.com","IsDeleted":false,"DeletedDate":null,"CreatedDate":"2023-10-03T01:06:51.5290749-04:00","ModifiedDate":null,"Id":"41bf61b2-fad3-4d04-8a6a-8be20d6f179a"},{"FirstName":"Lowell","LastName":"Romaguera","EmailAddress":"Lowell.Romaguera@yahoo.com","IsDeleted":false,"DeletedDate":null,"CreatedDate":"2023-10-03T01:06:51.5290751-04:00","ModifiedDate":null,"Id":"1b1962f3-0472-4595-8589-4affbbc08d7c"},{"FirstName":"Dora","LastName":"Gorczany","EmailAddress":"Dora.Gorczany@yahoo.com","IsDeleted":false,"DeletedDate":null,"CreatedDate":"2023-10-03T01:06:51.5290753-04:00","ModifiedDate":null,"Id":"594ae46f-9709-49d2-81c3-0a8fc08832f1"},{"FirstName":"Jonathon","LastName":"Cassin","EmailAddress":"Jonathon_Cassin@yahoo.com","IsDeleted":false,"DeletedDate":null,"CreatedDate":"2023-10-03T01:06:51.5290754-04:00","ModifiedDate":null,"Id":"a06c4883-13f8-4f99-aa00-f78a13363389"},{"FirstName":"Mario","LastName":"Halvorson","EmailAddress":"Mario.Halvorson@hotmail.com","IsDeleted":false,"DeletedDate":null,"CreatedDate":"2023-10-03T01:06:51.529077-04:00","ModifiedDate":null,"Id":"2ac3242e-09b8-4ba3-91df-ae32d1d582f5"},{"FirstName":"Catherine","LastName":"Stroman","EmailAddress":"Catherine_Stroman@gmail.com","IsDeleted":false,"DeletedDate":null,"CreatedDate":"2023-10-03T01:06:51.5290772-04:00","ModifiedDate":null,"Id":"9c697da7-ab5f-4d59-8f07-e92e58d2ddf7"},{"FirstName":"Joy","LastName":"Mertz","EmailAddress":"Joy.Mertz3@yahoo.com","IsDeleted":false,"DeletedDate":null,"CreatedDate":"2023-10-03T01:06:51.5290774-04:00","ModifiedDate":null,"Id":"6eb478ab-257a-4440-8861-2b052399f0c8"},{"FirstName":"Vicky","LastName":"Botsford","EmailAddress":"Vicky73@hotmail.com","IsDeleted":false,"DeletedDate":null,"CreatedDate":"2023-10-03T01:06:51.5290776-04:00","ModifiedDate":null,"Id":"137bb1f1-f97b-4489-a2ce-30ac2355d889"},{"FirstName":"Marty","LastName":"Crooks","EmailAddress":"Marty_Crooks5@gmail.com","IsDeleted":false,"DeletedDate":null,"CreatedDate":"2023-10-03T01:06:51.5290778-04:00","ModifiedDate":null,"Id":"53881316-84e3-40e4-8036-6e0f0ea9aa29"},{"FirstName":"Brenda","LastName":"Bernhard","EmailAddress":"Brenda.Bernhard@hotmail.com","IsDeleted":false,"DeletedDate":null,"CreatedDate":"2023-10-03T01:06:51.529078-04:00","ModifiedDate":null,"Id":"ae582e04-c28c-44ea-8b54-39a225210c60"},{"FirstName":"Aaron","LastName":"Gutmann","EmailAddress":"Aaron15@gmail.com","IsDeleted":false,"DeletedDate":null,"CreatedDate":"2023-10-03T01:06:51.5290781-04:00","ModifiedDate":null,"Id":"b60ecb71-d5c4-4d31-a0c7-77a2b51e589a"},{"FirstName":"Jeremy","LastName":"Wolf","EmailAddress":"Jeremy54@gmail.com","IsDeleted":false,"DeletedDate":null,"CreatedDate":"2023-10-03T01:06:51.5290783-04:00","ModifiedDate":null,"Id":"279d3b1e-9b02-4c85-8fa3-b5d950a08f14"},{"FirstName":"Lester","LastName":"Sporer","EmailAddress":"Lester_Sporer@hotmail.com","IsDeleted":false,"DeletedDate":null,"CreatedDate":"2023-10-03T01:06:51.5290785-04:00","ModifiedDate":null,"Id":"a7c1681e-bc76-485b-b035-c269c8cd7047"},{"FirstName":"Shirley","LastName":"O'Reilly","EmailAddress":"Shirley_OReilly@yahoo.com","IsDeleted":false,"DeletedDate":null,"CreatedDate":"2023-10-03T01:06:51.5290786-04:00","ModifiedDate":null,"Id":"65ff2f9c-9dc4-48a1-b14e-8d9b21dc9725"},{"FirstName":"Francisco","LastName":"Mann","EmailAddress":"Francisco_Mann18@gmail.com","IsDeleted":false,"DeletedDate":null,"CreatedDate":"2023-10-03T01:06:51.5290788-04:00","ModifiedDate":null,"Id":"279d69e9-edbc-4767-83d3-d6d66bc9550e"},{"FirstName":"Helen","LastName":"Beier","EmailAddress":"Helen.Beier@hotmail.com","IsDeleted":false,"DeletedDate":null,"CreatedDate":"2023-10-03T01:06:51.529079-04:00","ModifiedDate":null,"Id":"52b33056-95c7-43f8-afea-6211e5d97241"},{"FirstName":"Becky","LastName":"VonRueden","EmailAddress":"Becky_VonRueden76@hotmail.com","IsDeleted":false,"DeletedDate":null,"CreatedDate":"2023-10-03T01:06:51.5290791-04:00","ModifiedDate":null,"Id":"93eb38d6-61d3-4091-9c92-8d6c68e679f1"},{"FirstName":"Corey","LastName":"Ruecker","EmailAddress":"Corey75@yahoo.com","IsDeleted":false,"DeletedDate":null,"CreatedDate":"2023-10-03T01:06:51.5290793-04:00","ModifiedDate":null,"Id":"361916b0-d23d-4d93-9cb5-161cbb92f4dc"},{"FirstName":"Angel","LastName":"Berge","EmailAddress":"Angel.Berge@hotmail.com","IsDeleted":false,"DeletedDate":null,"CreatedDate":"2023-10-03T01:06:51.5290795-04:00","ModifiedDate":null,"Id":"e2246fc7-fda4-47aa-9460-3a339eaf2689"},{"FirstName":"Jeremiah","LastName":"Kreiger","EmailAddress":"Jeremiah51@gmail.com","IsDeleted":false,"DeletedDate":null,"CreatedDate":"2023-10-03T01:06:51.5290796-04:00","ModifiedDate":null,"Id":"9bdf3b02-7250-4f60-8d3c-6400354cd383"},{"FirstName":"Ken","LastName":"Waelchi","EmailAddress":"Ken_Waelchi48@yahoo.com","IsDeleted":false,"DeletedDate":null,"CreatedDate":"2023-10-03T01:06:51.5290798-04:00","ModifiedDate":null,"Id":"42cc30b7-7b78-48f8-aaaf-60727342ccd4"},{"FirstName":"Judith","LastName":"Hickle","EmailAddress":"Judith_Hickle@yahoo.com","IsDeleted":false,"DeletedDate":null,"CreatedDate":"2023-10-03T01:06:51.52908-04:00","ModifiedDate":null,"Id":"598909ba-cf31-4cf9-8ee4-56ab871b2344"},{"FirstName":"Sheldon","LastName":"Conn","EmailAddress":"Sheldon_Conn56@gmail.com","IsDeleted":false,"DeletedDate":null,"CreatedDate":"2023-10-03T01:06:51.5290801-04:00","ModifiedDate":null,"Id":"01958d05-8fe8-410d-95c9-a3d411db33ba"},{"FirstName":"Kristy","LastName":"Schoen","EmailAddress":"Kristy53@hotmail.com","IsDeleted":false,"DeletedDate":null,"CreatedDate":"2023-10-03T01:06:51.5290803-04:00","ModifiedDate":null,"Id":"4dd6cb50-1591-4fef-af74-b3a4b21f67ff"},{"FirstName":"Natasha","LastName":"Dickinson","EmailAddress":"Natasha73@yahoo.com","IsDeleted":false,"DeletedDate":null,"CreatedDate":"2023-10-03T01:06:51.5290805-04:00","ModifiedDate":null,"Id":"b1d40584-920f-4625-b65e-aef5bb1311b0"},{"FirstName":"Greg","LastName":"Ruecker","EmailAddress":"Greg_Ruecker64@hotmail.com","IsDeleted":false,"DeletedDate":null,"CreatedDate":"2023-10-03T01:06:51.5290806-04:00","ModifiedDate":null,"Id":"3b780d15-6fcd-487a-8080-dcc9b0789b73"},{"FirstName":"Roxanne","LastName":"Schaden","EmailAddress":"Roxanne35@yahoo.com","IsDeleted":false,"DeletedDate":null,"CreatedDate":"2023-10-03T01:06:51.5290808-04:00","ModifiedDate":null,"Id":"ad0612b3-9c0b-460e-aae6-254568cd8772"},{"FirstName":"Bryan","LastName":"Towne","EmailAddress":"Bryan_Towne67@yahoo.com","IsDeleted":false,"DeletedDate":null,"CreatedDate":"2023-10-03T01:06:51.529081-04:00","ModifiedDate":null,"Id":"e85ad8b3-513d-471f-a3c0-58ca61952ee4"},{"FirstName":"Meghan","LastName":"Rau","EmailAddress":"Meghan_Rau@hotmail.com","IsDeleted":false,"DeletedDate":null,"CreatedDate":"2023-10-03T01:06:51.5290811-04:00","ModifiedDate":null,"Id":"387ba6cc-a748-4e5a-a457-514a738ba36e"},{"FirstName":"Joe","LastName":"Bailey","EmailAddress":"Joe48@hotmail.com","IsDeleted":false,"DeletedDate":null,"CreatedDate":"2023-10-03T01:06:51.5290813-04:00","ModifiedDate":null,"Id":"10b01c67-f374-4424-8fc8-cc2777203805"},{"FirstName":"Kenneth","LastName":"Gulgowski","EmailAddress":"Kenneth_Gulgowski68@gmail.com","IsDeleted":false,"DeletedDate":null,"CreatedDate":"2023-10-03T01:06:51.5290815-04:00","ModifiedDate":null,"Id":"dc09a21d-5ee4-4b8b-9e02-7f03a8f3ba1a"},{"FirstName":"Bobby","LastName":"Hills","EmailAddress":"Bobby_Hills@gmail.com","IsDeleted":false,"DeletedDate":null,"CreatedDate":"2023-10-03T01:06:51.5290816-04:00","ModifiedDate":null,"Id":"9df0a842-d702-42bb-bdcd-36c08d62316d"},{"FirstName":"Moses","LastName":"Crona","EmailAddress":"Moses.Crona26@yahoo.com","IsDeleted":false,"DeletedDate":null,"CreatedDate":"2023-10-03T01:06:51.5290818-04:00","ModifiedDate":null,"Id":"46aaf9c8-5fbe-4266-b1a9-f2c3e37b0a8a"},{"FirstName":"Carolyn","LastName":"Koepp","EmailAddress":"Carolyn49@hotmail.com","IsDeleted":false,"DeletedDate":null,"CreatedDate":"2023-10-03T01:06:51.529082-04:00","ModifiedDate":null,"Id":"0ff01dc5-8c7c-4e88-8037-2311185aacd0"},{"FirstName":"Elaine","LastName":"Wilderman","EmailAddress":"Elaine_Wilderman9@hotmail.com","IsDeleted":false,"DeletedDate":null,"CreatedDate":"2023-10-03T01:06:51.5290821-04:00","ModifiedDate":null,"Id":"44d90752-c0c2-467c-8312-13d112a5bf86"},{"FirstName":"Manuel","LastName":"Kreiger","EmailAddress":"Manuel94@gmail.com","IsDeleted":false,"DeletedDate":null,"CreatedDate":"2023-10-03T01:06:51.5290823-04:00","ModifiedDate":null,"Id":"f441dda3-28e8-48ce-8dfc-c51d6e108044"},{"FirstName":"Maurice","LastName":"Vandervort","EmailAddress":"Maurice_Vandervort64@gmail.com","IsDeleted":false,"DeletedDate":null,"CreatedDate":"2023-10-03T01:06:51.5290825-04:00","ModifiedDate":null,"Id":"0258d95e-fcd4-4ba3-8daf-f673e05dba51"},{"FirstName":"Kevin","LastName":"Sporer","EmailAddress":"Kevin47@gmail.com","IsDeleted":false,"DeletedDate":null,"CreatedDate":"2023-10-03T01:06:51.5290826-04:00","ModifiedDate":null,"Id":"cc3834ea-64a9-4436-9b39-ca9b88198313"},{"FirstName":"Lorene","LastName":"Olson","EmailAddress":"Lorene.Olson36@yahoo.com","IsDeleted":false,"DeletedDate":null,"CreatedDate":"2023-10-03T01:06:51.5290828-04:00","ModifiedDate":null,"Id":"8ba81957-c27b-4588-a1c2-2db99a6ce164"},{"FirstName":"Lisa","LastName":"Morissette","EmailAddress":"Lisa24@yahoo.com","IsDeleted":false,"DeletedDate":null,"CreatedDate":"2023-10-03T01:06:51.529083-04:00","ModifiedDate":null,"Id":"08310b5a-f131-44a9-9d54-23caba410df1"},{"FirstName":"Rogelio","LastName":"Kemmer","EmailAddress":"Rogelio59@gmail.com","IsDeleted":false,"DeletedDate":null,"CreatedDate":"2023-10-03T01:06:51.5290831-04:00","ModifiedDate":null,"Id":"305ea5e5-8625-459e-ad03-17f4453b0e48"},{"FirstName":"Alex","LastName":"Bahringer","EmailAddress":"Alex.Bahringer9@yahoo.com","IsDeleted":false,"DeletedDate":null,"CreatedDate":"2023-10-03T01:06:51.5290833-04:00","ModifiedDate":null,"Id":"0cd89e0a-3efe-4ca5-be9f-93e369db7b0f"},{"FirstName":"Danny","LastName":"Heidenreich","EmailAddress":"Danny25@yahoo.com","IsDeleted":false,"DeletedDate":null,"CreatedDate":"2023-10-03T01:06:51.5290834-04:00","ModifiedDate":null,"Id":"ff4628a0-0863-4cbe-9bb1-ec501be2409e"},{"FirstName":"Robin","LastName":"Gleason","EmailAddress":"Robin_Gleason13@hotmail.com","IsDeleted":false,"DeletedDate":null,"CreatedDate":"2023-10-03T01:06:51.5290836-04:00","ModifiedDate":null,"Id":"c498f5f6-83c0-4cdf-95ed-2aaefbd93782"},{"FirstName":"Dustin","LastName":"D'Amore","EmailAddress":"Dustin_DAmore@hotmail.com","IsDeleted":false,"DeletedDate":null,"CreatedDate":"2023-10-03T01:06:51.5290838-04:00","ModifiedDate":null,"Id":"4b7d61b1-a86a-4fed-b4f7-52a397d6909f"},{"FirstName":"Antonia","LastName":"Jaskolski","EmailAddress":"Antonia54@hotmail.com","IsDeleted":false,"DeletedDate":null,"CreatedDate":"2023-10-03T01:06:51.529084-04:00","ModifiedDate":null,"Id":"736f2a08-8424-4a20-86ab-94fe9be42b84"},{"FirstName":"Ernestine","LastName":"Hermiston","EmailAddress":"Ernestine_Hermiston20@gmail.com","IsDeleted":false,"DeletedDate":null,"CreatedDate":"2023-10-03T01:06:51.5290841-04:00","ModifiedDate":null,"Id":"431c07d6-adf5-4073-b893-ef3038a66c00"},{"FirstName":"Curtis","LastName":"Ortiz","EmailAddress":"Curtis29@hotmail.com","IsDeleted":false,"DeletedDate":null,"CreatedDate":"2023-10-03T01:06:51.5290843-04:00","ModifiedDate":null,"Id":"d43d4970-4464-4837-998e-79903e998daa"},{"FirstName":"Mario","LastName":"Welch","EmailAddress":"Mario_Welch70@yahoo.com","IsDeleted":false,"DeletedDate":null,"CreatedDate":"2023-10-03T01:06:51.5290845-04:00","ModifiedDate":null,"Id":"2150895f-c88c-434a-9081-ed4b94039d63"},{"FirstName":"Gilberto","LastName":"Willms","EmailAddress":"Gilberto48@gmail.com","IsDeleted":false,"DeletedDate":null,"CreatedDate":"2023-10-03T01:06:51.5290846-04:00","ModifiedDate":null,"Id":"fccb745b-3b0e-40fd-aa92-456f0537895e"},{"FirstName":"Courtney","LastName":"O'Kon","EmailAddress":"Courtney.OKon86@hotmail.com","IsDeleted":false,"DeletedDate":null,"CreatedDate":"2023-10-03T01:06:51.5290849-04:00","ModifiedDate":null,"Id":"153d2d8d-6963-44a9-a361-f2bec54cb83f"},{"FirstName":"Max","LastName":"Senger","EmailAddress":"Max_Senger74@yahoo.com","IsDeleted":false,"DeletedDate":null,"CreatedDate":"2023-10-03T01:06:51.529085-04:00","ModifiedDate":null,"Id":"eee674b1-6d3e-495b-8acc-fc7398ab8243"},{"FirstName":"Lucia","LastName":"Gusikowski","EmailAddress":"Lucia_Gusikowski@yahoo.com","IsDeleted":false,"DeletedDate":null,"CreatedDate":"2023-10-03T01:06:51.5290852-04:00","ModifiedDate":null,"Id":"ff5055d2-24dc-404d-a0a3-68f5ac362285"},{"FirstName":"Samantha","LastName":"Kuhn","EmailAddress":"Samantha_Kuhn20@gmail.com","IsDeleted":false,"DeletedDate":null,"CreatedDate":"2023-10-03T01:06:51.5290854-04:00","ModifiedDate":null,"Id":"fcbbcea4-069a-4631-9c33-06db2860ec4f"},{"FirstName":"Kristin","LastName":"Kutch","EmailAddress":"Kristin56@gmail.com","IsDeleted":false,"DeletedDate":null,"CreatedDate":"2023-10-03T01:06:51.5290855-04:00","ModifiedDate":null,"Id":"5e6e5694-8e40-4782-83d8-1b4f3bea687d"},{"FirstName":"Myra","LastName":"Corwin","EmailAddress":"Myra_Corwin@yahoo.com","IsDeleted":false,"DeletedDate":null,"CreatedDate":"2023-10-03T01:06:51.5290857-04:00","ModifiedDate":null,"Id":"c67c7499-6643-4881-bddd-8e29d3470112"},{"FirstName":"Seth","LastName":"Thompson","EmailAddress":"Seth_Thompson@yahoo.com","IsDeleted":false,"DeletedDate":null,"CreatedDate":"2023-10-03T01:06:51.5290859-04:00","ModifiedDate":null,"Id":"ba5b5755-8ef9-4bbd-9cb4-094247ffbd3e"},{"FirstName":"Patricia","LastName":"O'Kon","EmailAddress":"Patricia_OKon0@yahoo.com","IsDeleted":false,"DeletedDate":null,"CreatedDate":"2023-10-03T01:06:51.529086-04:00","ModifiedDate":null,"Id":"62347560-e5e5-465f-959b-6ce428669752"},{"FirstName":"Helen","LastName":"Johnson","EmailAddress":"Helen94@yahoo.com","IsDeleted":false,"DeletedDate":null,"CreatedDate":"2023-10-03T01:06:51.5290862-04:00","ModifiedDate":null,"Id":"f1bfc69c-2565-466c-aa66-52856eccb118"},{"FirstName":"Chelsea","LastName":"Parisian","EmailAddress":"Chelsea_Parisian82@yahoo.com","IsDeleted":false,"DeletedDate":null,"CreatedDate":"2023-10-03T01:06:51.5290864-04:00","ModifiedDate":null,"Id":"1133e150-299b-4e36-8167-8a13b47a3bd0"},{"FirstName":"Sheila","LastName":"Reynolds","EmailAddress":"Sheila_Reynolds@hotmail.com","IsDeleted":false,"DeletedDate":null,"CreatedDate":"2023-10-03T01:06:51.5290865-04:00","ModifiedDate":null,"Id":"6d57b024-aab4-419f-8be8-e4052408b1e5"},{"FirstName":"Jodi","LastName":"Sauer","EmailAddress":"Jodi5@hotmail.com","IsDeleted":false,"DeletedDate":null,"CreatedDate":"2023-10-03T01:06:51.5290867-04:00","ModifiedDate":null,"Id":"064915ae-5754-42ee-9fea-da5167684850"},{"FirstName":"Otis","LastName":"Considine","EmailAddress":"Otis44@hotmail.com","IsDeleted":false,"DeletedDate":null,"CreatedDate":"2023-10-03T01:06:51.5290869-04:00","ModifiedDate":null,"Id":"c8be2b62-5837-4d9d-b904-561a1fa8d6f1"},{"FirstName":"Jonathan","LastName":"Rippin","EmailAddress":"Jonathan98@hotmail.com","IsDeleted":false,"DeletedDate":null,"CreatedDate":"2023-10-03T01:06:51.529087-04:00","ModifiedDate":null,"Id":"cb6102da-fbe6-4199-940d-cbb831fd3f50"},{"FirstName":"Juanita","LastName":"Stanton","EmailAddress":"Juanita_Stanton92@gmail.com","IsDeleted":false,"DeletedDate":null,"CreatedDate":"2023-10-03T01:06:51.5290872-04:00","ModifiedDate":null,"Id":"f738acbf-0018-49cc-9621-9f5c350535d9"},{"FirstName":"Cesar","LastName":"Dickens","EmailAddress":"Cesar.Dickens@yahoo.com","IsDeleted":false,"DeletedDate":null,"CreatedDate":"2023-10-03T01:06:51.5290874-04:00","ModifiedDate":null,"Id":"edd69722-054e-483e-b7a1-06f9adf68a1e"},{"FirstName":"Ann","LastName":"Abshire","EmailAddress":"Ann.Abshire36@gmail.com","IsDeleted":false,"DeletedDate":null,"CreatedDate":"2023-10-03T01:06:51.5290875-04:00","ModifiedDate":null,"Id":"8264bc4f-4c7d-4626-ba1a-860d378c950b"},{"FirstName":"Simon","LastName":"Huel","EmailAddress":"Simon21@hotmail.com","IsDeleted":false,"DeletedDate":null,"CreatedDate":"2023-10-03T01:06:51.5290877-04:00","ModifiedDate":null,"Id":"1661287a-0ba9-483c-94a9-9bdf70610950"},{"FirstName":"Lynda","LastName":"Gerhold","EmailAddress":"Lynda44@hotmail.com","IsDeleted":false,"DeletedDate":null,"CreatedDate":"2023-10-03T01:06:51.5290878-04:00","ModifiedDate":null,"Id":"68faac64-1216-4e97-aad6-2a411ad29b8f"},{"FirstName":"Alberta","LastName":"Ferry","EmailAddress":"Alberta32@gmail.com","IsDeleted":false,"DeletedDate":null,"CreatedDate":"2023-10-03T01:06:51.529088-04:00","ModifiedDate":null,"Id":"99e67433-5158-4493-ab97-f616a632c2ee"},{"FirstName":"Cameron","LastName":"Kunde","EmailAddress":"Cameron_Kunde85@hotmail.com","IsDeleted":false,"DeletedDate":null,"CreatedDate":"2023-10-03T01:06:51.5290882-04:00","ModifiedDate":null,"Id":"82538f24-a2c9-4811-8acb-a74a4513286b"},{"FirstName":"Ora","LastName":"Kris","EmailAddress":"Ora_Kris89@hotmail.com","IsDeleted":false,"DeletedDate":null,"CreatedDate":"2023-10-03T01:06:51.5290883-04:00","ModifiedDate":null,"Id":"3a771063-480a-4caf-8856-227f63edf71f"},{"FirstName":"Clara","LastName":"Stanton","EmailAddress":"Clara_Stanton@hotmail.com","IsDeleted":false,"DeletedDate":null,"CreatedDate":"2023-10-03T01:06:51.5290885-04:00","ModifiedDate":null,"Id":"070753a0-7a70-4d38-b185-9ffe24a05652"},{"FirstName":"Carole","LastName":"Witting","EmailAddress":"Carole_Witting81@hotmail.com","IsDeleted":false,"DeletedDate":null,"CreatedDate":"2023-10-03T01:06:51.5290887-04:00","ModifiedDate":null,"Id":"c50c735a-3073-4efe-8556-feec4be73ce0"}]